del2phen/__init__.py
del2phen/analysis/__init__.py
del2phen/analysis/__main__.py
del2phen/analysis/analyze.py
del2phen/analysis/data_objects.py
del2phen/analysis/gene_set.py
del2phen/analysis/hpo.py
del2phen/analysis/network.py
del2phen/analysis/patient_comparison.py
del2phen/analysis/phenotype_homogeneity.py
del2phen/analysis/phenotype_prediction.py
del2phen/analysis/plotting.py
del2phen/analysis/utilities.py
del2phen/dashboard/__init__.py
del2phen/dashboard/__main__.py
del2phen/dashboard/dashboard_general.py
del2phen/dashboard/assets/c6_logo.png
del2phen/dashboard/assets/c6_logo_white.png
del2phen/resources/HI_Predictions.v3.bed
del2phen/resources/HI_Predictions.v3.chr6.bed
del2phen/resources/__init__.py
del2phen/resources/custom_phenotypes.tsv
del2phen/resources/default_termset.yaml
del2phen/resources/dominant_genes.txt
del2phen/resources/gnomad.v2.1.1.lof_metrics.by_gene.6.tsv
del2phen/resources/gnomad.v2.1.1.lof_metrics.by_gene.txt
del2phen/resources/hg19.ensGene.transcripts.gtf.gz
del2phen/resources/hpo.obo
del2phen/resources/human_g1k_v37_phiX.dict
del2phen/resources/phaplo.tsv
del2phen/resources/phaplo_scores.chr6.tsv
Del2Phen-2024.7.15.dist-info/METADATA
Del2Phen-2024.7.15.dist-info/WHEEL
Del2Phen-2024.7.15.dist-info/entry_points.txt
Del2Phen-2024.7.15.dist-info/top_level.txt
Del2Phen-2024.7.15.dist-info/RECORD
