Metadata-Version: 2.1
Name: Del2Phen
Version: 2024.7.15
Summary: Del2Phen, a tool to predict phenotypes associated with copy-number variants based on similar CNVs in patient data.
Home-page: https://github.com/Chromosome-6-Project/Del2Phen
Author: T.D. Medina
Author-email: tylerdanmedina@gmail.com
Requires-Python: >=3.9, !=3.10
Requires-Dist: dash
Requires-Dist: dash-bootstrap-components
Requires-Dist: mygene
Requires-Dist: networkx
Requires-Dist: numpy
Requires-Dist: pandas
Requires-Dist: plotly
Requires-Dist: pronto
Requires-Dist: PyYAML
Requires-Dist: venn
